{
  "dataType": {
    "type": "double",
    "precision": 8,
    "scale": -2147483648
  },
  "expressions": [
    {
      "expressionId": "62AA36EDE4EC11D387E80010A4E86DEC",
      "expression": {
        "text": "qty_sold * discount",
        "tokens": [
          {
            "level": "resolved",
            "state": "initial",
            "value": "qty_sold",
            "type": "column_reference",
            "target": {
              "versionId": "02CA5783482DD0CC7555FDB1A554B6A4",
              "acg": 255,
              "primaryLocale": "en-US",
              "objectId": "8D6792AA11D3E4981000E787EC6DE8A4",
              "subType": "column",
              "name": "qty_sold"
            }
          },
          {
            "level": "resolved",
            "state": "initial",
            "value": "*",
            "type": "character",
            "target": {
              "versionId": "83B5F8527A43D460E34D10ABE3CA7425",
              "acg": 255,
              "primaryLocale": "en-US",
              "objectId": "8107C312DD9911D3B98100C04F2233EA",
              "subType": "function",
              "name": "*",
              "description": "Returns the product of two values."
            }
          },
          {
            "level": "resolved",
            "state": "initial",
            "value": "discount",
            "type": "column_reference",
            "target": {
              "versionId": "966EFBE9486A36CE1E7B0887421DF342",
              "acg": 255,
              "primaryLocale": "en-US",
              "objectId": "8D6792AD11D3E4981000E787EC6DE8A4",
              "subType": "column",
              "name": "discount"
            }
          },
          {
            "level": "resolved",
            "state": "initial",
            "value": "",
            "type": "end_of_text"
          }
        ]
      },
      "tables": [
        {
          "objectId": "8D6793CE11D3E4981000E787EC6DE8A4",
          "subType": "logical_table",
          "name": "ORDER_DETAIL"
        }
      ]
    }
  ],
  "extensions": [],
  "entryLevel": [
    {
      "objectId": "96ED3EC811D5B117C000E78A4CC5F24F",
      "subType": "attribute",
      "name": "Day"
    },
    {
      "objectId": "8D679D3F11D3E4981000E787EC6DE8A4",
      "subType": "attribute",
      "name": "Employee"
    },
    {
      "objectId": "8D679D4211D3E4981000E787EC6DE8A4",
      "subType": "attribute",
      "name": "Item"
    },
    {
      "objectId": "8D679D4611D3E4981000E787EC6DE8A4",
      "subType": "attribute",
      "name": "Order"
    },
    {
      "objectId": "95FA2DC34EC9063FD6C400B4FA8570E0",
      "subType": "attribute",
      "name": "Phone Usage"
    }
  ],
  "versionId": "4FA8047946CDC3763C70F0AA1E38FD8F",
  "acg": 255,
  "primaryLocale": "en-US",
  "subType": "fact",
  "name": "Discount",
  "id": "62AA36C011D3E4EC1000E887EC6DE8A4"
}